dmb/__init__.py
dmb/constants.py
dmb/crypt.py
dmb/dmb.py
dmb/dmbreader.py
dmb/dmbwriter.py
dmb/json.py
dmb/tree.py
dmb/util.py
dmb/value.py
pydmb-0.2.0.dist-info/DESCRIPTION.rst
pydmb-0.2.0.dist-info/METADATA
pydmb-0.2.0.dist-info/metadata.json
pydmb-0.2.0.dist-info/RECORD
pydmb-0.2.0.dist-info/top_level.txt
pydmb-0.2.0.dist-info/WHEEL
