Metadata-Version: 2.0
Name: pydmb
Version: 0.2.0
Summary: DMB file parser for python
Home-page: https://github.com/baliame/pydmb
Author: Baliame
Author-email: akos.toth@cheppers.com
License: MIT
Keywords: byond dmb development library
Platform: UNKNOWN
Classifier: Intended Audience :: Developers
Classifier: Topic :: Software Development :: Libraries
Classifier: License :: OSI Approved :: MIT License
Classifier: Programming Language :: Python :: 3
Classifier: Programming Language :: Python :: 3.2
Classifier: Programming Language :: Python :: 3.3
Classifier: Programming Language :: Python :: 3.4
Classifier: Programming Language :: Python :: 3.5
